LICENSE.md
MANIFEST.in
README.md
requirements.txt
setup.cfg
setup.py
doc/Makefile
doc/make.bat
doc/build/doctrees/FAQ.doctree
doc/build/doctrees/accuracy.doctree
doc/build/doctrees/algobase.doctree
doc/build/doctrees/basic_algorithms.doctree
doc/build/doctrees/building_custom_algo.doctree
doc/build/doctrees/co_clustering.doctree
doc/build/doctrees/dataset.doctree
doc/build/doctrees/dump.doctree
doc/build/doctrees/environment.pickle
doc/build/doctrees/evaluate.doctree
doc/build/doctrees/getting_started.doctree
doc/build/doctrees/index.doctree
doc/build/doctrees/knn_inspired.doctree
doc/build/doctrees/matrix_factorization.doctree
doc/build/doctrees/model_selection.doctree
doc/build/doctrees/notation_standards.doctree
doc/build/doctrees/prediction_algorithms.doctree
doc/build/doctrees/prediction_algorithms_package.doctree
doc/build/doctrees/predictions_module.doctree
doc/build/doctrees/reader.doctree
doc/build/doctrees/similarities.doctree
doc/build/doctrees/slope_one.doctree
doc/build/doctrees/trainset.doctree
doc/build/html/.buildinfo
doc/build/html/FAQ.html
doc/build/html/accuracy.html
doc/build/html/algobase.html
doc/build/html/basic_algorithms.html
doc/build/html/building_custom_algo.html
doc/build/html/co_clustering.html
doc/build/html/dataset.html
doc/build/html/dump.html
doc/build/html/evaluate.html
doc/build/html/genindex.html
doc/build/html/getting_started.html
doc/build/html/index.html
doc/build/html/knn_inspired.html
doc/build/html/matrix_factorization.html
doc/build/html/model_selection.html
doc/build/html/notation_standards.html
doc/build/html/objects.inv
doc/build/html/prediction_algorithms.html
doc/build/html/prediction_algorithms_package.html
doc/build/html/predictions_module.html
doc/build/html/py-modindex.html
doc/build/html/reader.html
doc/build/html/search.html
doc/build/html/searchindex.js
doc/build/html/similarities.html
doc/build/html/slope_one.html
doc/build/html/trainset.html
doc/build/html/_modules/index.html
scikit_surprise.egg-info/PKG-INFO
scikit_surprise.egg-info/SOURCES.txt
scikit_surprise.egg-info/dependency_links.txt
scikit_surprise.egg-info/entry_points.txt
scikit_surprise.egg-info/requires.txt
scikit_surprise.egg-info/top_level.txt
