Metadata-Version: 1.1
Name: scikit-surprise
Version: 1.0.5
Summary: An easy-to-use library for recommender systems.
Home-page: http://surpriselib.com
Author: Nicolas Hug
Author-email: contact@nicolas-hug.com
License: GPLv3+
Keywords: recommender recommendation system
Platform: UNKNOWN
Classifier: Development Status :: 5 - Production/Stable
Classifier: Intended Audience :: Developers
Classifier: Intended Audience :: Education
Classifier: Intended Audience :: Science/Research
Classifier: Topic :: Scientific/Engineering
Classifier: License :: OSI Approved :: BSD License
Classifier: Programming Language :: Python :: 3
Classifier: Programming Language :: Python :: 2.7
